[
  {
    "id": "the-legal-services-authorities-act-1987-0000",
    "title": "THE LEGAL SERVICES AUTHORITIES ACT, 1987",
    "section": "",
    "category": "Legal",
    "text": "THE LEGAL SERVICES AUTHORITIES ACT, 1987\n\n________\n\nARRANGEMENT OF SECTIONS\n\n________\n\nCHAPTER I\n\nPRELIMINARY\n\nSECTIONS\n\n1. Short title, extent and commencement.\n\n2. Definitions.\n\nCHAPTER II\n\nTHE NATIONAL LEGAL SERVICES AUTHORITY\n\n3. Constitution of the National Legal Services Authority.\n\n3A. Supreme Court Legal Services Committee.\n\n4. Functions of the Central Authority.\n\n5. Central Authority to work in coordination with other agencies.\n\nCHAPTER III\n\nSTATE LEGAL SERVICES AUTHORITY\n\n6. Constitution of State Legal Services Authority.\n\n7. Functions of the State Authority.\n\n8. State Authority to act in coordination with other agencies, etc., and be subject to directions given\n\nby the Central Authority.\n\n8A. High Court Legal Services Committee.\n\n9. District Legal Services Authority.\n\n10. Functions of the District Authority\n\n11. District Authority to act in coordination with other agencies and be subject to directions given by\n\nthe Central Authority, etc.\n\n11A. Taluk Legal Services Committee.\n\n11B. Functions of Taluk Legal Services Committee.\n\nCHAPTER IV\n\nENTITLEMENT TO LEGAL SERVICES\n\n12. Criteria for giving legal services.\n\n13. Entitlement of legal services.\n\nCHAPTER V\n\nFINANCE, ACCOUNTS AND AUDIT\n\n14. Grants by the Central Government.\n\n| Short title, extent and commencement. |  |\n| --- | --- |\n| Definitions. |  |\n\n| 3. | Constitution of the National Legal Services Authority. |\n| --- | --- |\n| 3A. Supreme Court Legal Services Committee. |  |\n| 4. 5. | Functions of the Central Authority. |\n|  | Central Authority to work in coordination with other agencies. |\n\n| 6. 7. 8. | Constitution of State Legal Services Authority. |\n| --- | --- |\n|  | Functions of the State Authority. |\n|  | State Authority to act in coordination with other agencies, etc., and be subject to directions given |\n|  | by the Central Authority. |\n| 8A. High Court Legal Services Committee. |  |\n| 9. 10. 11. | District Legal Services Authority. |\n|  | Functions of the District Authority |\n|  | District Authority to act in coordination with other agencies and be subject to directions given by |\n|  | the Central Authority, etc. |\n| 11A. Taluk Legal Services Committee. |  |\n| 11B. Functions of Taluk Legal Services Committee. |  |",
    "keywords": [],
    "document_type": "act",
    "jurisdiction": "India",
    "source": "THE LEGAL SERVICES AUTHORITIES ACT, 1987 .pdf",
    "importance": 5
  },
  {
    "id": "the-legal-services-authorities-act-1987-0001",
    "title": "THE LEGAL SERVICES AUTHORITIES ACT, 1987",
    "section": "",
    "category": "Legal",
    "text": "|  | ENTITLEMENT TO LEGAL SERVICES |\n| --- | --- |\n| Criteria for giving legal services. |  |\n| Entitlement of legal services. |  |\n\nSECTIONS\n\n15. National Legal Aid Fund.\n\n16. State Legal Aid Fund.\n\n17. District Legal Aid Fund.\n\n18. Accounts and audit.\n\nCHAPTER VI\n\nLOKADALATS\n\n19. Organisation of Lok Adalats.\n\n20. Cognizance of cases by Lok Adalats.\n\n21. Award of Lok Adalat.\n\n22. Powers of Lok Adalat or Permanent Lok Adalat.\n\nCHAPTER VIA\n\nPRE-LITIGATION CONCILIATION AND SETTLEMENT\n\n22A. Definitions.\n\n22B. Establishment of Permanent Lok Adalats.\n\n22C. Cognizance of cases by Permanent Lok Adalat.\n\n22D. Procedure of Permanent Lok Adalat.\n\n22E.Award of Permanent Lok Adalat to be final.\n\nCHAPTER VII\n\nMISCELLANEIOUS\n\n23. Members and staff of Authorities, Committees and Lok Adalats to be public servants.\n\n24. Protection of action taken in good faith.\n\n25. Act to have overriding effect.\n\n26. Power to remove difficulties.\n\n27. Power of Central Government to make rules.\n\n28. Power of State Government to make rules.\n\n29.Power of Central Authority to make regulations.\n\n29A. Power of State Authority to make regulations.\n\n30. Laying of rules and regulations\n\n| MISCELLANEIOUS 23. Members and staff of Authorities, Committees and Lok Adalats to be public servants. 24. Protection of action taken in good faith. 25. Act to have overriding effect. 26. Power to remove difficulties. 27. Power of Central Government to make rules. 28. Power of State Government to make rules. 29.Power of Central Authority to make regulations. 29A. Power of State Authority to make regulations. 30. Laying of rules and regulations |  | MISCELLANEIOUS |  |\n| --- | --- | --- | --- |\n|  | Members and staff of Authorities, Committees and Lok Adalats to be public servants. |  |  |\n|  | Protection of action taken in good faith. |  |  |\n|  | Act to have overriding effect. |  |  |\n|  | Power to remove difficulties. |  |  |\n| 27. Power of Central Government to make rules. |  |  |  |\n| 28. Power of State Government to make rules. |  |  |  |\n| 29.Power of Central Authority to make regulations. |  |  |  |\n| 29A. Power of State Authority to make regulations. |  |  |  |\n| 30. Laying of rules and regulations |  |  |  |",
    "keywords": [
      "award",
      "lok adalat"
    ],
    "document_type": "act",
    "jurisdiction": "India",
    "source": "THE LEGAL SERVICES AUTHORITIES ACT, 1987 .pdf",
    "importance": 5
  },
  {
    "id": "the-legal-services-authorities-act-1987-0002",
    "title": "THE LEGAL SERVICES AUTHORITIES ACT, 1987",
    "section": "",
    "category": "Legal",
    "text": "THE LEGAL SERVICES AUTHORITIES ACT, 1987\n\nACT NO. 39 OF 1987\n\n[11th October, 1987.]\n\nAn Act to constitute legal services authorities to provide free and competent legal services to the\n\nweaker sections of the society to ensure that opportunities for securing justice are not denied\n\nto any citizen by reason of economic or other disabilities, and to organize Lok Adalats to\n\nsecure that the operation of the legal system promotes justice on a basis of equal opportunity.\n\nBE it enacted by the Parliament in the Thirty-eighth Year of the Republic of India as follows:—\n\nCHAPTER I\n\nPRELIMINARY\n\n1. Short title, extent and commencement.—This Act may be called the Legal Services Authorities\n\nAct, 1987.\n\n(2) It extends to the whole of India, 1***.\n\n(3) It shall come into force on such date2 as the Central Government may, by notification, appoint;\n\nand different dates may be appointed for different provisions of this Act and for different States, and any\n\nreference to commencement in any provision of this Act in relation to any State shall be construed as a\n\nreference to the commencement of that provision in that State.\n\n2. Definitions.—In this Act, unless the context otherwise requires,—\n\n3[(a) “case” includes a suit or any proceeding before a court;\n\n(aa) “Central Authority” means the National Legal Services Authority constituted under section3;\n\n(aaa) “court” means a civil, criminal or revenue court and includes any tribunal or any other\n\nauthority constituted under any law for the time being in force, to exercise judicial or quasi-judicial\n\nfunctions;]\n\n(b) “District Authority” means a District Legal Services Authorityconstituted under section9;\n\n4[(bb) “High Court Legal Services Committee” means a High Court Legal Services Committee\n\nconstituted under section8A;]\n\n(c) “legal service” includes the rendering of any service in the conduct of any case or other legal\n\nproceeding before any court or other authority or tribunal and the giving of advice on any legal",
    "keywords": [
      "lok adalat"
    ],
    "document_type": "act",
    "jurisdiction": "India",
    "source": "THE LEGAL SERVICES AUTHORITIES ACT, 1987 .pdf",
    "importance": 5
  },
  {
    "id": "the-legal-services-authorities-act-1987-0003",
    "title": "THE LEGAL SERVICES AUTHORITIES ACT, 1987",
    "section": "",
    "category": "Legal",
    "text": "matter;\n\n(d)“Lok Adalat” means a Lok Adalat organised under Chapter VI;\n\n(e) “notification” means a notification published in the Official Gazette;\n\n(f) “prescribed” means prescribed by rules made under this Act;\n\n3[(ff) “regulations” means regulations made under this Act;]\n\n(g) “scheme” means any scheme framed by the Central Authority, a State Authority or a District\n\nAuthority for the purpose of giving effect to any of the provisions of this Act;\n\n(h) “State Authority” means a State Legal Services Authority constituted under section6;\n\n(i) “State Government” includes the administrator of a Union territory appointed by the President\n\nunder article 239 of the Constitution;\n\n1. The words “except the State of Jammu and Kashmir” omitted by Act 34 of 2019, s. 95 and the Fifth Schedule (w.e.f. 31-10-\n\n2019).\n\n2. 9th November, 1995, vide notification No. S.O. 893(E), dated 9th November, 1995, see Gazette of India, Extraordinary, Part\n\nII, sec. 3(ii).\n\n3. Subs. by Act 59 of 1994, s. 2, for clause (a) (w.e.f. 29-10-1994).\n\n4. Ins. by s. 2, ibid. (w.e.f. 29-10-1994).\n\n1[(j) “Supreme Court Legal Services Committee” means the Supreme Court Legal Services\n\nCommittee constituted under section3A;\n\n(k) “Taluk Legal Services Committee” means a Taluk Legal Services Committee constituted\n\nunder section11A.]\n\n(2) Any reference in this Act to any other enactment or any provision thereof shall, in relation to an\n\narea in which such enactment or provision is not in force, be construed as a reference to the corresponding\n\nlaw or the relevant provision of the corresponding law, if any, in force in that area.\n\nCHAPTER II\n\nTHE NATIONAL LEGAL SERVICES AUTHORITY\n\n2[3. Constitution of the National Legal Services Authority.—(1) The Central Government shall\n\nconstitute a body to be called the National Legal Services Authority to exercise the powers and perform\n\nthe functions conferred on, or assigned to, the Central Authority under this Act.",
    "keywords": [
      "lok adalat"
    ],
    "document_type": "act",
    "jurisdiction": "India",
    "source": "THE LEGAL SERVICES AUTHORITIES ACT, 1987 .pdf",
    "importance": 5
  },
  {
    "id": "the-legal-services-authorities-act-1987-0004",
    "title": "THE LEGAL SERVICES AUTHORITIES ACT, 1987",
    "section": "",
    "category": "Legal",
    "text": "(2) The Central Authority shall consist of—\n\n(a) theChief Justice of India who shall be the Patron-in-Chief;\n\n(b) a serving or retired Judge of the Supreme Court to be nominated by the President, in\n\nconsultation with the Chief Justice of India, who shall be the Executive Chairman; and\n\n(c) such number of other members, possessing such experience and qualifications, as may be\n\nprescribed by the Central Government, to be nominated by that Government in consultation with the\n\nChief Justice of India.\n\n(3) The Central Government shall, in consultation with the Chief Justice of India, appoint a person to\n\nbe the Member-Secretary of the Central Authority, possessing such experience and qualifications as may\n\nbe prescribed by that Government, to exercise such powers and perform such duties under the Executive\n\nChairman of the Central Authority as may be prescribed by that Government or as may be assigned to\n\nhim by the Executive Chairman of that Authority.\n\n(4) The terms of office and other conditions relating thereto, of members and the Member-Secretary\n\nof the Central Authority shall be such as may be prescribed by the Central Government in consultation\n\nwith the Chief Justice of India.\n\n(5) The Central Authority may appoint such number of officers and other employees as may be\n\nprescribed by the Central Government, in consultation with the Chief Justice of India, for the efficient\n\ndischarge of its functions under this Act.\n\n(6) The officers and other employees of the Central Authority shall be entitled to such salary and\n\nallowances and shall be subject to such other conditions of service as may be prescribed by the Central\n\nGovernment in consultation with the Chief Justice of India.\n\n(7) The administrative expenses of the Central Authority, including the salaries, allowances and\n\npensions payable to the Member-Secretary, officers and other employees of the Central Authority, shall",
    "keywords": [],
    "document_type": "act",
    "jurisdiction": "India",
    "source": "THE LEGAL SERVICES AUTHORITIES ACT, 1987 .pdf",
    "importance": 5
  },
  {
    "id": "the-legal-services-authorities-act-1987-0005",
    "title": "THE LEGAL SERVICES AUTHORITIES ACT, 1987",
    "section": "",
    "category": "Legal",
    "text": "be defrayed out of the Consolidated Fund of India.\n\n(8) All orders and decisions of the Central Authority shall be authenticated by the Member-Secretary\n\nor any other officer of the Central Authority duly authorised by the Executive Chairman of that Authority.\n\n(9) No act or proceeding of the Central Authority shall be invalid merely on the ground of the\n\nexistence of any vacancy in, or any defect in the constitution of, the Central Authority.\n\n3A. Supreme Court Legal Services Committee.—(1) The Central Authority shall constitute a\n\ncommittee to be called the Supreme Court Legal Services Committee for the purpose of exercising such\n\n1. Ins. by Act 59 of 1994, s. 2 (w.e.f. 29-10-1994).\n\n2. Subs. by s. 3, ibid., for section 3 (w.e.f. 29-10-1994).\n\npowers and performing such functions as may be determined by regulations made by the Central\n\nAuthority.\n\n(2) The Committee shall consist of—\n\n(a) a sitting Judge of the Supreme Court who shall be the Chairman; and\n\n(b) such number of other members possessing such experience and qualifications as may be\n\nprescribed by the Central Government,\n\nto be nominated by the Chief Justice of India.\n\n(3) The Chief Justice of India shall appoint a person to be the Secretary to the Committee, possessing\n\nsuch experience and qualifications as may be prescribed by the Central Government.\n\n(4) The terms of office and other conditions relating thereto, of the members and Secretary of the\n\nCommittee shall be such as may be determined by regulations made by the Central Authority.\n\n(5) The Committee may appoint such number of officers and other employees as may be prescribed\n\nby the Central Government, in consultation with the Chief Justice of India, for the efficient discharge of\n\nits functions.\n\n(6) The officers and other employees of the Committee shall be entitled to such salary and allowances",
    "keywords": [],
    "document_type": "act",
    "jurisdiction": "India",
    "source": "THE LEGAL SERVICES AUTHORITIES ACT, 1987 .pdf",
    "importance": 5
  },
  {
    "id": "the-legal-services-authorities-act-1987-0006",
    "title": "THE LEGAL SERVICES AUTHORITIES ACT, 1987",
    "section": "",
    "category": "Legal",
    "text": "and shall be subject to such other conditions of service as may be prescribed by the Central Government\n\nin consultation with the Chief Justice of India.]\n\n4. Functions of the Central Authority.—The Central Authority shall 1*** perform all or any of the\n\nfollowing functions, namely:—\n\n(a) lay down policies and principles for making legal services available under the provisions of\n\nthis Act;\n\n(b) frame the most effective and economical schemes for the purpose of making legal services\n\navailable under the provisions of this Act;\n\n(c) utilise the funds at its disposal and make appropriate allocations of funds to the State\n\nAuthorities and District Authorities;\n\n(d) take necessary steps by way of social justice litigation with regard to consumer protection,\n\nenvironmental protection or any other matter of special concern to the weaker sections of the society\n\nand for this purpose, give training to social workers in legal skills;\n\n(e) organise legal aid camps, especially in rural areas, slums or labour colonies with the dual\n\npurpose of educating the weaker sections of the society as to their rights as well as encouraging the\n\nsettlement of disputes through LokAdalats;\n\n(f) encourage the settlement of disputes by way of negotiations, arbitration and conciliation;\n\n(g) undertake and promote research in the field of legal services with special reference to the need\n\nfor such services among the poor;\n\n(h) to do all things necessary for the purpose of ensuring commitment to the fundamental duties\n\nof citizens under Part IVA of the Constitution;\n\n(i) monitor and evaluate implementation of the legal aid programmes at periodic intervals and\n\nprovide for independent evaluation of programmes and schemes implemented in whole or in part by\n\nfunds provided under this Act;\n\n1. The words “, subject to the general directions of the Central Government,” omitted by Act of 59 of 1994, s. 4 (w.e.f. 29-10-",
    "keywords": [
      "arbitration",
      "settlement"
    ],
    "document_type": "act",
    "jurisdiction": "India",
    "source": "THE LEGAL SERVICES AUTHORITIES ACT, 1987 .pdf",
    "importance": 5
  },
  {
    "id": "the-legal-services-authorities-act-1987-0007",
    "title": "THE LEGAL SERVICES AUTHORITIES ACT, 1987",
    "section": "",
    "category": "Legal",
    "text": "1994).\n\n1[(j) provide grants-in-aid for specific schemes to various voluntary social service institutions and\n\nthe State and District Authorities, from out of the amounts placed at its disposal for the\n\nimplementation of the legal services schemes under the provisions of this Act;]\n\n(k) develop, in consultation with the Bar Council of India, programmes for clinical legal\n\neducation and promote guidance and supervise the establishment and working of legal services clinics\n\nin universities, law colleges and other institutions;\n\n(l) take appropriate measures for spreading legal literacy and legal awareness amongst the people\n\nand, in particular, to educate weaker sections of the society about the rights, benefits and\n\nprivileges guaranteed by social welfare legislations and other enactments as well as administrative\n\nprogrammes and measures;\n\n(m) make special efforts to enlist the support of voluntary social welfare institutions working at\n\nthe grass-root level, particularly among the Scheduled Castes and the Scheduled Tribes, women and\n\nrural and urban labour; and\n\n(n) coordinate and monitor the functioning of 2[State Authorities, District Authorities, Supreme\n\nCourt Legal Services Committee, High Court Legal Services Committees, Taluk Legal Services\n\nCommittees and voluntary social service institutions] and other legal services organisations and give\n\ngeneral directions for the proper implementation of the legal services programmes.\n\n5. Central Authority to work in coordination with other agencies.—In the discharge of its\n\nfunctions under this Act, the Central Authority shall, wherever appropriate, act in coordination with other\n\ngovernmental and non-governmental agencies, universities and others engaged in the work of promoting\n\nthe cause of legal services to the poor.\n\nCHAPTER III\n\nSTATE LEGAL SERVICESAUTHORITY\n\n3[6. Constitution of State Legal Services Authority.—(1) Every State Government shall constitute a\n\nbody to be called the Legal Services Authority for the State to exercise the powers and perform the\n\nfunctions conferred on, or assigned to, a State Authority under this Act.",
    "keywords": [],
    "document_type": "act",
    "jurisdiction": "India",
    "source": "THE LEGAL SERVICES AUTHORITIES ACT, 1987 .pdf",
    "importance": 5
  },
  {
    "id": "the-legal-services-authorities-act-1987-0008",
    "title": "THE LEGAL SERVICES AUTHORITIES ACT, 1987",
    "section": "",
    "category": "Legal",
    "text": "(2) A State Authority shall consist of—\n\n(a) the Chief Justice of the High Court who shall be the Patron-in-Chief;\n\n(b) a serving or retired Judge of the High Court, to be nominated by the Governor, in consultation\n\nwith the Chief Justice of the High Court, who shall be the Executive Chairman; and\n\n(c) such number of other members, possessing such experience and qualifications as may be\n\nprescribed by the State Government, to be nominated by that Government in consultation with the\n\nChief Justice of the High Court.\n\n(3) The State Government shall, in consultation with the Chief Justice of the High Court, appoint a\n\nperson belonging to the State Higher Judicial Service, not lower in rank than that of a District Judge, as\n\nthe Member-Secretary of the State Authority, to exercise such powers and perform such duties under the\n\nExecutive Chairman of the State Authority as may be prescribed by that Government or as may be\n\nassigned to him by the Executive Chairman of that Authority.\n\nProvided that a person functioning as Secretary of a State Legal Aid and Advice Board immediately\n\nbefore the date of constitution of the State Authority may be appointed as Member-Secretary of that\n\nAuthority, even if he is not qualified to be appointed as such under this sub-section, for a period not\n\nexceeding five years.\n\n1. Subs. by Act 59 of 1994, s. 4, for clause (j) (w.e.f. 29-10-1994).\n\n2. Subs. by s. 4, ibid., for “State and District Authorities and other voluntary social welfare institutions” (w.e.f. 29-10-1994).\n\n3. Subs. by s. 5,ibid., for section 6 (w.e.f. 29-10-1994).\n\n(4) The terms of office and other conditions relating thereto, of members and the Member-Secretary\n\nof the State Authority shall be such as may be prescribed by the State Government in consultation with\n\nthe Chief Justice of the High Court.",
    "keywords": [],
    "document_type": "act",
    "jurisdiction": "India",
    "source": "THE LEGAL SERVICES AUTHORITIES ACT, 1987 .pdf",
    "importance": 5
  },
  {
    "id": "the-legal-services-authorities-act-1987-0009",
    "title": "THE LEGAL SERVICES AUTHORITIES ACT, 1987",
    "section": "",
    "category": "Legal",
    "text": "(5) The State Authority may appoint such number of officers and other employees as may be\n\nprescribed by the State Government, in consultation with the Chief Justice of the High Court, for the\n\nefficient discharge of its functions under thisAct.\n\n(6) The officers and other employees of the State Authority shall be entitled to such salary and\n\nallowances and shall be subject to such other conditions of service as may be prescribed by the State\n\nGovernment in consultation with the Chief Justice of the High Court.\n\n(7) The administrative expenses of the State Authority, including the salaries, allowances and\n\npensions payable to the Member-Secretary, officers and other employees of the State Authorityshall be\n\ndefrayed out of the Consolidated Fund of the State.\n\n(8) All orders and decisions of the State Authority shall be authenticated by the Member-Secretary or\n\nany other officer of the State Authority duly authorised by the Executive Chairman of the State Authority.\n\n(9) No act or proceeding of a State Authority shall be invalid merely on the ground of the existence of\n\nany vacancy in, or any defect in the constitution of, the State Authority.]\n\n7. Functions of the State Authority.—(1) It shall be the duty of the State Authority to give to effect\n\nto the policy and directions of the Central Authority.\n\n(2) Without prejudice to the generality of the functions referred to in sub-section(1), the State\n\nAuthority shall perform all or any of the following functions, namely:—\n\n(a) give legal service to persons who satisfy the criteria laid down under this Act;\n\n(b) conduct1[LokAdalats, including LokAdalats for High Court cases];\n\n(c) undertake preventive and strategic legal aid programmes; and\n\n(d) perform such other functions as the State Authority may, in consultation with the 2[Central\n\nAuthority], fix by regulations.\n\n3[8. State Authority to act in coordination with other agencies., etc., and be subject to directions",
    "keywords": [],
    "document_type": "act",
    "jurisdiction": "India",
    "source": "THE LEGAL SERVICES AUTHORITIES ACT, 1987 .pdf",
    "importance": 5
  },
  {
    "id": "the-legal-services-authorities-act-1987-0010",
    "title": "THE LEGAL SERVICES AUTHORITIES ACT, 1987",
    "section": "",
    "category": "Legal",
    "text": "given by the Central Authority.—In the discharge of its functions the State Authority shall\n\nappropriately act in coordination with other governmentalagencies, non-governmental voluntary social\n\nservice institutions, universities and other bodies engaged in the work of promoting the cause of legal\n\nservices to the poor and shall also be guided by such directions as the Central Authority may give to it in\n\nwriting.\n\n8A. High Court Legal Services Committee.—(1) The State Authority shall constitute a Committee\n\nto be called the High Court Legal Services Committee for every High Court, for the purpose of exercising\n\nsuch powers and performing such functions as may be determined by regulations made by the State\n\nAuthority.\n\n(2) The Committee shall consist of—\n\n(a) a sitting Judge of the High Court who shall be the Chairman; and\n\n(b) such number of other members possessing such experience and qualifications as may be\n\ndetermined by regulations made by the State Authority,\n\nto be nominated by the Chief Justice of the High Court.\n\n(3) The Chief Justice of the High Court shall appoint a Secretary to the Committee possessing such\n\nexperience and qualifications as may be prescribed by the State Government.\n\n1. Subs. by Act 59 of 1994, s. 6, for “LokAdalats” (w.e.f. 29-10-1994).\n\n2. Subs. by s. 6, ibid., for “Central Government” (w.e.f. 29-10-1994).\n\n3. Subs. by s. 7, ibid., for sections 8 and 9 (w.e.f. 29-10-1994).\n\n|  | 3[8. State Authority to act in coordination with other agencies., etc., and be subject to directions |  |\n| --- | --- | --- |\n| given by the Central Authority. |  | —In the discharge of its functions the State Authority shall |\n\n(4) The terms of office and other conditions relating thereto, of the members and Secretary of the\n\nCommittee shall be such as may be determined by regulations made by the State Authority.",
    "keywords": [],
    "document_type": "act",
    "jurisdiction": "India",
    "source": "THE LEGAL SERVICES AUTHORITIES ACT, 1987 .pdf",
    "importance": 5
  },
  {
    "id": "the-legal-services-authorities-act-1987-0011",
    "title": "THE LEGAL SERVICES AUTHORITIES ACT, 1987",
    "section": "",
    "category": "Legal",
    "text": "(5) The Committee may appoint such number of officers and other employees as may be prescribed\n\nby the State Governmentin consultation with the Chief Justice of the High Court for the efficient\n\ndischarge of its functions.\n\n(6) The officers and other employees of the Committee shall be entitled to such salary and allowances\n\nand shall be subject to such other conditions of Service as may be prescribed by the State Government in\n\nconsultation with the Chief Justice of the High Court.\n\n9. District Legal Services Authority.—(1) The State Government shall, in consultation with the\n\nChief Justice of the High Court, constitute a body to be called the District Legal Services Authority for\n\nevery District in the State to exercise the powers and perform the functions conferred on, or assigned to,\n\nthe District Authority under this Act.\n\n(2) A District Authority shall consist of—\n\n(a) the District Judge who shall be its Chairman; and\n\n(b) such number of other members, possessing such experience and qualifications, as may be\n\nprescribed by the State Government, to be nominated by that Government in consultation with the\n\nChief Justice of the High Court.\n\n(3) The State Authority shall, in consultation with the Chairman of the District Authority, appoint a\n\nperson belonging to the State Judicial Service not lower in rank than that of a Subordinate Judge or Civil\n\nJudge posted at the seat of the DistrictJudiciary as Secretary of the District Authority to exercise such\n\npowers and perform such duties under the Chairman of that Committee as may be assigned to him by\n\nsuch Chairman.\n\n(4) The terms of office and other conditions relating thereto, of members and Secretary of the District\n\nAuthority shall be such as may be determined by regulations made by the State Authority in consultation\n\nwith the Chief Justice of the High Court.",
    "keywords": [],
    "document_type": "act",
    "jurisdiction": "India",
    "source": "THE LEGAL SERVICES AUTHORITIES ACT, 1987 .pdf",
    "importance": 5
  },
  {
    "id": "the-legal-services-authorities-act-1987-0012",
    "title": "THE LEGAL SERVICES AUTHORITIES ACT, 1987",
    "section": "",
    "category": "Legal",
    "text": "(5) The District Authority may appoint such number of officers and other employees as may be\n\nprescribed by the State Government in consultation with the Chief Justice of the High Court for the\n\nefficient discharge of its functions.\n\n(6) The officers and other employees of the District Authority shall be entitled to such salary and\n\nallowances and shall be subject to such other conditions of service as may be prescribed by the State\n\nGovernment in consultation with the Chief Justice of the High Court.\n\n(7) The administrative expenses of every District Authority, including the salaries, allowances and\n\npensions payable to the Secretary, officers and other employees of the District Authority, shall be\n\ndefrayed out of the Consolidated Fund of the State.\n\n(8) All orders and decisions of the District Authority shall be authenticated by the Secretary or by any\n\nother officer of the District Authority duly authorised by the Chairman of that Authority.\n\n(9) No act or proceeding of the District Authority shall be invalid merely on the ground of the\n\nexistence of any vacancy in, or any defect in the constitution of, the District Authority.]\n\n10. Functions of the District Authority.—(1) It shall be the duty of every District Authority to\n\nperform such of the functions of the State Authority in the District as may be delegated to it from time to\n\ntime by the State Authority.\n\n(2) Without prejudice to the generality of the functions referred to in sub-section (1), the District\n\nAuthority may perform all or any of the following functions, namely:—\n\n1[(a) coordinate the activities of the Taluk Legal Services Committee and other legal services in\n\nthe District;]\n\n1. Subs. by Act 59 of 1994, s. 8, for clause (a) (w.e.f. 29-10-1994).\n\n(b) organize Lok Adalats within the District; and\n\n(c) perform such other functions as the State Authority may 1*** fix by regulations.\n\n11. District Authority to act in coordination with other agencies and be subject to directions",
    "keywords": [
      "lok adalat"
    ],
    "document_type": "act",
    "jurisdiction": "India",
    "source": "THE LEGAL SERVICES AUTHORITIES ACT, 1987 .pdf",
    "importance": 5
  },
  {
    "id": "the-legal-services-authorities-act-1987-0013",
    "title": "THE LEGAL SERVICES AUTHORITIES ACT, 1987",
    "section": "",
    "category": "Legal",
    "text": "given by the Central Authority, etc.—In the discharge of its functions under this Act, the District\n\nAuthority shall, wherever appropriate, act in coordination with other governmental and non-governmental\n\ninstitutions, universities and others engaged in the work of promoting the cause of legal services to the\n\npoor and shall also be guided by such directions as the Central Authority or the State Authority may give\n\nto it in writing.\n\n2[11A. Taluk Legal Services Committee.—(1) The State Authority may constitute a Committee, to\n\nbe called the Taluk Legal Services Committee, for each taluk or mandal or for group of taluks or mandals.\n\n(2) The Committee shall consist of—\n\n(a) The 3[senior-most Judicial Officer] operating within the jurisdiction of the Committee who\n\nshall be the ex officio Chairman; and\n\n(b) such number of other members, possessing such experience and qualifications, as may be\n\nprescribed by the State Government, to be nominated by that Government in consultation with the\n\nChief Justice of the High Court.\n\n(3) The Committee may appoint such number of officers and other employees as may be prescribed\n\nby the State Government in consultation with the Chief Justice of the High Court for the efficient\n\ndischarge of its functions.\n\n(4) The officers and other employees of the Committee shall be entitled to such salary and allowances\n\nand shall be subject to such other conditions of service as may be prescribed by the State Government in\n\nconsultation with the Chief Justice of the High Court.\n\n(5) The administrative expenses of the Committee shall be defrayed out of the District Legal Aid\n\nFund by the District Authority.\n\n11B. Functions of Taluk Legal Services Committee.—The Taluk Legal Services Committee may\n\nperform all or any of the following functions, namely:—\n\n(a) co-ordinate the activities of legal services in the taluk;\n\n(b) organize Lok Adalats within the taluk; and\n\n(c) perform such other functions as the District Authority may assign to it.]",
    "keywords": [
      "lok adalat"
    ],
    "document_type": "act",
    "jurisdiction": "India",
    "source": "THE LEGAL SERVICES AUTHORITIES ACT, 1987 .pdf",
    "importance": 5
  },
  {
    "id": "the-legal-services-authorities-act-1987-0014",
    "title": "THE LEGAL SERVICES AUTHORITIES ACT, 1987",
    "section": "",
    "category": "Legal",
    "text": "CHAPTER IV\n\nENTITLEMENT TO LEGAL SERVICES\n\n12. Criteria for giving legal services.—Every person who has to file or defend a case shall be\n\nentitled to legal services under this Act if that person is—\n\n(a) a member of a Scheduled Caste or Scheduled Tribe;\n\n(b) a victim of trafficking in human beings or begar as referred to in article 23 of the\n\nConstitution;\n\n(c) a woman or a child;\n\n4[(d) a person with disability as defined in clause (i) of section2 of the Persons With Disabilities\n\n(Equal Opportunities, Protection of Rights and Full Participation) Act, 1995 (1 of 1996);]\n\n1. The words “, in consultation with the State Government,” omitted by Act 59 of 1994, s. 8 (w.e.f. 29-10-1994).\n\n2. Ins. by s. 9, ibid. (w.e.f. 29-10-1994).\n\n3. Subs. by Act 37 of 2002, s. 2, for “senior Civil Judge” (w.e.f. 11-6-2002).\n\n4. Subs. by Act 1 of 1996, s. 74, for clause (d) (w.e.f. 7-2-1996).\n\n|  | 11. District Authority to act in coordination with other agencies and be subject to directions |  |\n| --- | --- | --- |\n| given by the Central Authority, etc. |  | —In the discharge of its functions under this Act, the District |\n\n(e) a person under circumstances of underserved want such as being a victim of a mass disaster,\n\nethnic, violence, caste atrocity, flood, drought, earthquake or industrial disaster; or\n\n(f) an industrial workman; or\n\n(g) in custody, including custody in a protective home within the meaning of clause (g) of\n\nsection2 of the Immoral Traffic (Prevention) Act, 1956 (104 of 1956), or in a juvenile home within\n\nthe meaning of clause (j) of section 2 of the Juvenile Justice Act, 1986 (53 of 1986), or in a\n\npsychiatric hospital or psychiatric nursing home within the meaning of clause (g) of section2 of the",
    "keywords": [],
    "document_type": "act",
    "jurisdiction": "India",
    "source": "THE LEGAL SERVICES AUTHORITIES ACT, 1987 .pdf",
    "importance": 5
  },
  {
    "id": "the-legal-services-authorities-act-1987-0015",
    "title": "THE LEGAL SERVICES AUTHORITIES ACT, 1987",
    "section": "",
    "category": "Legal",
    "text": "Mental Health Act, 1987 (14 of 1987); or\n\n1[(h) in receipt of annual income less than rupees nine thousand or such other higher amount as\n\nmay be prescribed by the State Government, if the case is before a court other than the Supreme\n\nCourt, and less than rupees twelve thousand or such other higher amount as may be prescribed by the\n\nCentral Government, if the case is before the Supreme Court.]\n\n13. Entitlement of legal services.—(1) Persons who satisfy all or any of the criteria specified in\n\nsection 12 shall be entitled to receive legal services provided that the concerned Authority is satisfied that\n\nsuch person has aprima facie case to prosecute or to defend.\n\n(2) An affidavit made by a person as to his income may be regarded as sufficient for making him\n\neligible to the entitlement of legal services under this Act unless the concerned Authority has reason to\n\ndisbelieve such affidavit.\n\nCHAPTER V\n\nFINANCE, ACCOUNTS AND AUDIT\n\n14. Grants by the Central Government.—The Central Government shall, after due appropriation\n\nmade by Parliament by law in this behalf, pay to the Central Authority, by way of grants, such sums of\n\nmoney as the Central Government may think fit for being utilised for the purposes of this Act.\n\n15. National Legal Aid Fund.—(1) The Central Authority shall establish a fund to be called the\n\nNational Legal Aid Fund and there shall be credited thereto—\n\n(a) all sums of money given as grants by the Central Government under section 14;\n\n(b) any grants or donations that may be made to the Central Authority by any other person for the\n\npurposes of this Act;\n\n(c) any amount received by the Central Authority under the orders of any court or from any other\n\nsource.\n\n(2) The National Legal Aid Fund shall be applied for meeting—\n\n(a) the cost of legal services provided under this Act including grants made to State Authorities;",
    "keywords": [],
    "document_type": "act",
    "jurisdiction": "India",
    "source": "THE LEGAL SERVICES AUTHORITIES ACT, 1987 .pdf",
    "importance": 5
  },
  {
    "id": "the-legal-services-authorities-act-1987-0016",
    "title": "THE LEGAL SERVICES AUTHORITIES ACT, 1987",
    "section": "",
    "category": "Legal",
    "text": "2[(b) the cost of legal services provided by the Supreme Court Legal Services Committee;\n\n(c) any other expenses which are required to be met by the Central Authority.]\n\n16. State Legal Aid Fund.—(1) A State Authority shall establish a fund to be called the State Legal\n\nAid Fund and there shall be credited thereto—\n\n(a) all sums of money paid to it or any grants by the Central Authority for the purposes of this\n\nAct;\n\n(b) any grants or donations that may be made to the State Authority by the State Government or\n\nby any person for the purposes of this Act;\n\n(c) any other amount received by the State Authority under the orders of any court or from any\n\nother source.\n\n1. Subs. by Act 59 of 1994, s. 10, for clause (h) (w.e.f. 29-10-1994).\n\n2. Subs. by s. 11, ibid., for clause (b) (w.e.f. 29-10-1994).\n\n(2) A State Legal Aid Fund shall be applied for meeting—\n\n(a) the cost of functions referred to in section 7;\n\n1[(b) the cost of legal services provided by the High Court Legal Services Committee;\n\n(c) any other expenses which are required to be met by the State Authority.]\n\n17. District Legal Aid Fund.—(1) Every District Authority shall establish a fund to be called the\n\nDistrict Legal Aid Fund and there shall be credited thereto—\n\n(a) all sums of money paid or any grants made by the State Authority to the District Authority for\n\nthe purposes of this Act;\n\n2[(b) any grants or donations that may be made to the District Authority by any person, with the\n\nprior approval of the State Authority, for the purposes of this Act;]\n\n(c) anyother amount received by the District Authority under the orders of any court or from any\n\nother source.\n\n(2) A District Legal Aid Fund shall be applied for meeting—\n\n(a) the cost of functions referred to in section 10 3[and 11B];\n\n(b) any other expenses which are required to be met by the District Authority.\n\n18. Accounts and audit.—(1) The Central Authority, State Authority, or the District Authority",
    "keywords": [],
    "document_type": "act",
    "jurisdiction": "India",
    "source": "THE LEGAL SERVICES AUTHORITIES ACT, 1987 .pdf",
    "importance": 5
  },
  {
    "id": "the-legal-services-authorities-act-1987-0017",
    "title": "THE LEGAL SERVICES AUTHORITIES ACT, 1987",
    "section": "",
    "category": "Legal",
    "text": "(hereinafter referred to in this section as ‘the authority’), as the case may be, shall maintain proper\n\naccounts and other relevant records and prepare an annual statement of accounts including the income and\n\nexpenditure account and the balance-sheet in such form and in such manner as may be prescribed by the\n\nCentral Government in consultation with the Comptroller and Auditor-General of India.\n\n(2) The accounts of the Authorities shall be audited by the Comptroller and Auditor-General of India\n\nat such intervals as may be specified by him and any expenditure incurred in connection with such audit\n\nshall be payable by the Authority concerned to the Comptroller and Auditor-General of India.\n\n(3) The Comptroller and Auditor-General of India and any other person appointed by him in\n\nconnection with the auditing of the accounts of an Authority under this Act shall have the same rights and\n\nprivileges and authority in connection with such audit as the Comptroller and Auditor-General of India\n\nhas in connection with the auditing of the Government accounts and, in particular, shall have the right to\n\ndemand the production of books, accounts, connected vouchers and other documents and papers and to\n\ninspect any of the offices of the Authorities under this Act.\n\n(4) The accounts of the Authorities, as certified by the Comptroller and Auditor-General of India or\n\nany other person appointed by him in this behalf together with the audit report thereon, shall be forwarded\n\nannually by the Authorities to the Central Government or the State Governments, as the case may be.\n\n4[(5) The Central Government shall cause the accounts and the audit report received by it under sub-\n\nsection (4) to be laid, as soon as may be after they are received, before each House of Parliament.\n\n(6) The State Government shall cause the accounts and the audit report received by it under sub-",
    "keywords": [],
    "document_type": "act",
    "jurisdiction": "India",
    "source": "THE LEGAL SERVICES AUTHORITIES ACT, 1987 .pdf",
    "importance": 5
  },
  {
    "id": "the-legal-services-authorities-act-1987-0018",
    "title": "THE LEGAL SERVICES AUTHORITIES ACT, 1987",
    "section": "",
    "category": "Legal",
    "text": "section (4) to be laid, as soon as may be after they are received, before the State Legislature.]\n\nCHAPTER VI\n\nLOK ADALATS\n\n5[19. Organisation of Lok Adalats.—(1) Every State Authority or District Authority or the Supreme\n\nCourt Legal Services Committee or every High Court Legal Services Committee or, as the case may be,\n\n1. Subs. by Act 59 of 1994, s. 12, for clause (b) (w.e.f. 29-10-1994).\n\n2. Subs. by s. 13, ibid., for clause (b) (w.e.f. 29-10-1994).\n\n3. Ins. by s. 13, ibid. (w.e.f. 29-10-1994).\n\n4. Ins. by s. 14, ibid. (w.e.f. 29-10-1994).\n\n5. Subs. by s. 15, ibid., for sections 19 and 20 (w.e.f. 29-10-1994).\n\nTaluk Legal Services Committee may organize Lok Adalats at such intervals and places and for\n\nexercising such jurisdiction and for such areas as it thinks fit.\n\n(2) Every Lok Adalat organised for an area shall consist of such number of—\n\n(a) serving or retired judicial officers; and\n\n(b) other persons,\n\nof the area as may be specified by the State Authority or the District Authority or the Supreme Court\n\nLegal Services Committee or the High Court Legal Services Committee, or as the case may be, the Taluk\n\nLegal Services Committee, organising such Lok Adalat.\n\n(3) The experience and qualifications of other persons referred to in clause (b) of sub-section (2) for\n\nLok Adalats organised by the Supreme Court Legal Services Committee shall be such as may be\n\nprescribed by the Central Government in consultation with the Chief Justice of India.\n\n(4) The experience and qualifications of other persons referred to in clause (b) of sub-section (2) for\n\nLok Adalats other than referred to in sub-section (3) shall be such as may be prescribed by the State\n\nGovernment in consultation with the Chief Justice of the High Court.\n\n(5) A Lok Adalat shall have jurisdiction to determine and to arrive at a compromise or settlement",
    "keywords": [
      "jurisdiction",
      "lok adalat"
    ],
    "document_type": "act",
    "jurisdiction": "India",
    "source": "THE LEGAL SERVICES AUTHORITIES ACT, 1987 .pdf",
    "importance": 5
  },
  {
    "id": "the-legal-services-authorities-act-1987-0019",
    "title": "THE LEGAL SERVICES AUTHORITIES ACT, 1987",
    "section": "",
    "category": "Legal",
    "text": "between the parties to a dispute in respect of—\n\n(i) any case pending before; or\n\n(ii) any matter which is falling within the jurisdiction of, and is not brought before,\n\nany Court for which the Lok Adalat is organised:\n\nProvided that the Lok Adalat shall have no jurisdiction in respect of any case or matter relating to an\n\noffence not compoundable under any law.\n\n20. Cognizance of cases by Lok Adalats.—(1) Where in any case referred to in clause (i) of\n\nsub-section (5) of section 19,—\n\n(i)(a) the parties thereof agree; or\n\n(b) one of the parties thereof makes an application to the Court,\n\nfor referring the case to the Lok Adalat for settlement and if such court isprima facie satisfied that there\n\nare chances of such settlement; or\n\n(ii) thecourt is satisfied that the matter is an appropriate one to be taken cognizance of by the Lok\n\nAdalat,\n\nthe Court shall refer the case to the Lok Adalat:\n\nProvided that no case shall be referred to the Lok Adalat under sub-clause (b) of clause (i) or clause\n\n(ii) by such court except after giving a reasonable opportunity of being heard to the parties.\n\n(2) Notwithstanding anything contained in any cither law for the time being in force, the Authority or\n\nCommittee organising the Lok Adalat under sub-section (1) of section19 may, on receipt of an application\n\nfrom any one of the parties to any matter referred to in clause (ii) of sub-section (5) of section 19 that\n\nsuch matter needs to be determined by a Lok Adalat, refer such matter to the Lok Adalat, for\n\ndetermination:\n\nProvided that no matter shall be referred to the Lok Adalat except after giving a reasonable\n\nopportunity of being heard to the other party.\n\n(3) Where any case is referred to a Lok Adalat under sub-section (1) or where a reference has been",
    "keywords": [
      "jurisdiction",
      "lok adalat",
      "settlement"
    ],
    "document_type": "act",
    "jurisdiction": "India",
    "source": "THE LEGAL SERVICES AUTHORITIES ACT, 1987 .pdf",
    "importance": 5
  },
  {
    "id": "the-legal-services-authorities-act-1987-0020",
    "title": "THE LEGAL SERVICES AUTHORITIES ACT, 1987",
    "section": "",
    "category": "Legal",
    "text": "made to it under sub-section (2), the Lok Adalat shall proceed to dispose of the case or matter and arrive\n\nat a compromise or settlement between the parties.\n\n(4) Every Lok Adalat shall, while determining any reference before it under this Act, act with utmost\n\nexpedition to arrive at a compromise or settlement between the parties and shall be guided by the\n\nprinciples of justice, equity, fair play and other legal principles.\n\n(5) Where no award is made by the Lok Adalat on the ground that no compromise or settlementcould\n\nbe arrived at between the parties, the record of the case shall be returned by it to the court, from which the\n\nreference has been received under sub-section (1) for disposal in accordance with law.\n\n(6) Where no award is made by the Lok Adalat on the ground that no compromise or settlement could\n\nbe arrived at between the parties, in a matter referred to in sub-section (2), that Lok Adalat shall advice\n\nthe parties to seek remedy in a court.\n\n(7) Where the record of the case if returned under sub-section (5) to the court, such court shall\n\nproceed to deal with such case from the stage which was reached before such reference under sub-section\n\n(1).]\n\n21. Award of Lok Adalat.—1[(1) Every award of the Lok Adalat shall be deemed to be a decree of a\n\ncivil court or, as the case may be, an order of any other court and where a compromise or settlement has\n\nbeen arrived at, by a Lok Adalat in a case referred to it under sub-section(1) of section 20, the court-fee\n\npaid in such case shall be refunded in the manner provided under the Court-fees Act, 1870 (7 of 1870).]\n\n(2) Every award made by a Lok Adalat shall be final and binding on all the parties to the dispute, and",
    "keywords": [
      "award",
      "civil court",
      "compromise",
      "lok adalat",
      "settlement"
    ],
    "document_type": "act",
    "jurisdiction": "India",
    "source": "THE LEGAL SERVICES AUTHORITIES ACT, 1987 .pdf",
    "importance": 5
  },
  {
    "id": "the-legal-services-authorities-act-1987-0021",
    "title": "THE LEGAL SERVICES AUTHORITIES ACT, 1987",
    "section": "",
    "category": "Legal",
    "text": "no appeal shall lie to any court against the award.\n\n22. Powers of 2[Lok Adalat or Permanent Lok Adalat.]—(1) The 2[Lok Adalat or Permanent Lok\n\nAdalat] shall, for the purposes of holding any determination under this Act, have the same powers as are\n\nvested in a Civil Court under the Code of Civil Procedure, 1908 (5 of 1908), while trying a suit in respect\n\nof the following matters, namely:—\n\n(a) the summoning and enforcing the attendance of any witness and examining him on oath;\n\n(b) the discovery and production of any document;\n\n(c) the reception of evidence on affidavits;\n\n(d) the requisitioning of any public record or document or copy of such record or document from\n\nany court or office; and\n\n(e) such other matters as may be prescribed.\n\n(2) Without prejudice to the generality of the powers contained in sub-section (1), every 2[Lok Adalat\n\nor Permanent Lok Adalat] shall have the requisite powers to specify its own procedure for the\n\ndetermination of any dispute coming before it.\n\n(3) All proceedings before a 2[Lok Adalat or Permanent Lok Adalat] shall be deemed to be judicial\n\nproceedings within the meaning of sections 193,219 and 228 of the Indian Penal Code (45 of 1860) and\n\nevery 2[Lok Adalat or Permanent Lok Adalat] shall be deemed to be a Civil Court for the purpose of\n\nsection195 and Chapter XXVI of the Code of Criminal Procedure, 1973 (2 of 1974).\n\n3[CHAPTER VIA\n\nPRE-LITIGATION CONCILIATION AND SETTLEMENT\n\n22A. Definitions.—In this Chapter and for the purposes of sections 22 and 23, unless the context\n\notherwise requires,—\n\n(a) “Permanent Lok Adalat” means a Permanent Lok Adalat established under sub-section (1) of\n\nsection22B;\n\n1. Subs. by Act 59 of 1994, s. 16, for sub-section (1) (w.e.f. 29-10-1994),\n\n2. Subs. by Act 37 of 2002, s. 3, for “Lok Adalat” (w.e.f. 11-6-2002).\n\n3. Ins. by s. 4, ibid. (w.e.f. 11-6-2002).\n\n(b) “public utility service” means any—\n\n(i) transport service for the carriage of passengers or goods by air, road or water; or\n\n(ii) postal, telegraph or telephone service; or\n\n(iii) supply of power, light or water to the public by any establishment; or\n\n(iv) system of public conservancy or sanitation; or\n\n(v) service in hospital or dispensary; or",
    "keywords": [
      "civil court",
      "lok adalat"
    ],
    "document_type": "act",
    "jurisdiction": "India",
    "source": "THE LEGAL SERVICES AUTHORITIES ACT, 1987 .pdf",
    "importance": 5
  },
  {
    "id": "the-legal-services-authorities-act-1987-0022",
    "title": "THE LEGAL SERVICES AUTHORITIES ACT, 1987",
    "section": "",
    "category": "Legal",
    "text": "(vi)insurance service,\n\nand includes any service which the Central Government or the State Government, as the case may be,\n\nin the public interest, by notification, declare to be a public utility service for the purposes of this\n\nChapter.\n\n22B. Establishment of Permanent Lok Adalats.—(1) Notwithstanding anything contained in\n\nsection19, the Central Authority or, as the case may be, every State Authority shall, by notification,\n\nestablish Permanent Lok Adalats at such places and for exercising such jurisdiction in respect of one or\n\nmore public utility services and for such areas as may be specified in the notification.\n\n(2) Every Permanent Lok Adalat established for an area notified under sub-section (1) shall consist\n\nof—\n\n(a) a person who is, or has been, a district judge or additional district judge or has held judicial\n\noffice higher in rank than that of a district judge, shall be the Chairman of the Permanent Lok Adalat;\n\nand\n\n(b) two other persons having adequate experience in public utility service to be nominated by the\n\nCentral Government or, as the case may be, the State Government on the recommendation of the\n\nCentral Authority or, as the case may be, the State Authority,\n\nappointed by the Central Authority or, as the case may be, the State Authority, establishing such\n\nPermanent Lok Adalat and the other terms and conditions of the appointment of the Chairman and other\n\npersons referred to in clause (b) shall be such as may be prescribed by the Central Government.\n\n22C. Cognizance of cases by Permanent Lok Adalat.—(1) Any party to a dispute may, before the\n\ndispute is brought before any court, make an application to the Permanent Lok Adalat for the settlement\n\nof dispute:\n\nProvided that the Permanent Lok Adalat shall not have jurisdiction in respect of any matter relating to\n\nan offence not compoundable under any law:",
    "keywords": [
      "jurisdiction",
      "lok adalat"
    ],
    "document_type": "act",
    "jurisdiction": "India",
    "source": "THE LEGAL SERVICES AUTHORITIES ACT, 1987 .pdf",
    "importance": 5
  },
  {
    "id": "the-legal-services-authorities-act-1987-0023",
    "title": "THE LEGAL SERVICES AUTHORITIES ACT, 1987",
    "section": "",
    "category": "Legal",
    "text": "Provided further that the Permanent Lok Adalat shall also not have jurisdiction in the matter where\n\nthe value of the property in dispute exceeds ten lakh rupees:\n\nProvided also that the Central Government, may by notification, increase the limit often lakh rupees\n\nspecified in the second proviso in consultation with the Central Authority.\n\n(2) After an application is made under sub-section(1) to the Permanent Lok Adalat, no party to that\n\napplication shall invoke jurisdiction of any court in the same dispute.\n\n(3) Where an application is made to a Permanent Lok Adalat under sub-section(1), it—\n\n(a) shall direct each party to the application to file before it a written statement, stating therein\n\nthe facts and nature of dispute under the application, points or issues in such dispute and grounds\n\nrelied in support of, or in opposition to, such points or issues, as the case may be, and such party\n\nmay supplement such statement with any document and other evidence which such party deems\n\nappropriate in proof of such facts and grounds and shall send a copy of such statement together with\n\na copy of such document and other evidence, if any, to each of the parties to the application;\n\n(b) may require any party to the application to file additional statement before it at any stage of\n\nthe conciliation proceedings;\n\n(c) shall communicate any document or statement received by it from any party to the\n\napplication to the other party, to enable such other party to present reply thereto.\n\n(4) When statement, additional statement and reply, if any, have been filed under sub-section(3), to\n\nthe satisfaction of the Permanent Lok Adalat, it shall conduct conciliation proceedings between the parties\n\nto the application in such manner as it thinks appropriate taking into account the circumstances of the\n\ndispute.\n\n(5) The Permanent Lok Adalat shall, during conduct of conciliation proceedings under",
    "keywords": [
      "jurisdiction",
      "lok adalat"
    ],
    "document_type": "act",
    "jurisdiction": "India",
    "source": "THE LEGAL SERVICES AUTHORITIES ACT, 1987 .pdf",
    "importance": 5
  },
  {
    "id": "the-legal-services-authorities-act-1987-0024",
    "title": "THE LEGAL SERVICES AUTHORITIES ACT, 1987",
    "section": "",
    "category": "Legal",
    "text": "sub-section(4), assist the parties in their attempt to reach an amicable settlement of the dispute in an\n\nindependent and impartial manner.\n\n(6) It shall be the duty of the every party to the application to cooperate in good faith with the\n\nPermanent Lok Adalat in conciliation of the dispute relating to the application and to comply with the\n\ndirection of the Permanent Lok Adalat to produce evidence and other related documents before it.\n\n(7) When a Permanent Lok Adalat, in the aforesaid conciliation proceedings, is of opinion that there\n\nexist elements of settlement in such proceedings which may be acceptable to the parties, it may formulate\n\nthe terms of a possible settlement of the dispute and give to the parties concerned for their observations\n\nand in case the parties reach at an agreement on the settlement of the dispute, they shall sign the\n\nsettlement agreement and the Permanent Lok Adalat shall pass an award in terms thereof and furnish a\n\ncopy of the same to each of the parties concerned.\n\n(8) Where the parties fail to reach at an agreement under sub-section (7), the Permanent Lok Adalat\n\nshall, if the dispute does not relate to any offence, decide the dispute.\n\n22D. Procedure of Permanent Lok Adalat.—The Permanent Lok Adalat shall, while conducting\n\nconciliation proceedings or deciding a dispute on merit under this Act, be guided by the principles of\n\nnatural justice, objectivity, fair play, equity and other principles of justice, and shall not be bound by the\n\nCode of Civil Procedure, 1908 (5 of 1908) and the Indian Evidence Act, 1872 (1 of 1872).\n\n22E. Award of Permanent Lok Adalat to be final.—(1) Every award of the Permanent Lok Adalat\n\nunder this Act made either on merit or in terms of a settlement agreement shall be final and binding on all",
    "keywords": [
      "award",
      "civil court",
      "lok adalat",
      "settlement"
    ],
    "document_type": "act",
    "jurisdiction": "India",
    "source": "THE LEGAL SERVICES AUTHORITIES ACT, 1987 .pdf",
    "importance": 5
  },
  {
    "id": "the-legal-services-authorities-act-1987-0025",
    "title": "THE LEGAL SERVICES AUTHORITIES ACT, 1987",
    "section": "",
    "category": "Legal",
    "text": "the parties thereto and on persons claiming under them.\n\n(2) Every award of the Permanent Lok Adalat under this Act shall be deemed to be a decree of a civil\n\ncourt.\n\n(3) The award made by the Permanent Lok Adalat under this Act shall be by a majority of the persons\n\nconstituting the Permanent Lok Adalat.\n\n(4) Every award made by the Permanent Lok Adalat under this Act shall be final and shall not be\n\ncalled in question in any original suit, application or execution proceeding.\n\n(5) The Permanent Lok Adalat may transmit any award made by it to a civil court having local\n\njurisdiction and such civil court shall execute the order as if it were a decree made by that court.]\n\nCHAPTER VII\n\nMISCELLANEOUS\n\n1[23. Members and staff of Authorities, Committees and Lok Adalats to be public servants.—\n\nThe members including Member-Secretary or, as the case may be, Secretary of the Central Authority, the\n\nState Authority, the District Authorities, the Supreme Court Legal Services Committee, High Court Legal\n\nServices Committees, Taluk Legal Services Committees and officers and other employees of such\n\nAuthorities, Committees and the 2[members of the Lok Adalats or the persons constituting Permanent Lok\n\nAdalats] shall be deemed to be public servants within the meaning of section21 of the Indian Penal Code\n\n(45 of 1860).\n\n1. Subs. by Act 59 of 1994, s. 17, for sections 23 and 24 (w.e.f. 29-10-1994),\n\n2. Subs. by Act 37 of 2002, s. 5, for “members of the LokAdalats” (w.e.f. 11-6-2002).\n\n24. Protection of action taken in good faith.—No suit, prosecution or other legal proceeding shall\n\nlie against—\n\n(a) the Central Government or State Government;\n\n(b) the Patron-in-Chief, Executive Chairman, members of, Member-Secretary or officers or other\n\nemployees of the Central Authority;\n\n(c) Patron-in-Chief, Executive Chairman, member, Member-Secretary or officers or other",
    "keywords": [
      "award",
      "civil court",
      "decree",
      "lok adalat"
    ],
    "document_type": "act",
    "jurisdiction": "India",
    "source": "THE LEGAL SERVICES AUTHORITIES ACT, 1987 .pdf",
    "importance": 5
  },
  {
    "id": "the-legal-services-authorities-act-1987-0026",
    "title": "THE LEGAL SERVICES AUTHORITIES ACT, 1987",
    "section": "",
    "category": "Legal",
    "text": "employees of the State Authority;\n\n(d) Chairman, Secretary, members or officers or other employees of the Supreme Court Legal\n\nServices Committee, High Court Legal Services Committees, Taluk Legal Services Committees or\n\nthe District Authority; or\n\n(e) any other person authorised by any of the Patron-in-Chief, Executive Chairman, Chairman,\n\nMember, Member-Secretary referred to in sub-clauses (b) to (d),\n\nfor anything which is in good faith done or intended to be done under the provisions of this Act or any\n\nrule or regulation made thereunder.]\n\n25. Act to have overriding effect.—The provisions of this Act shall have effect notwithstanding\n\nanything inconsistent therewith contained in any other law for the time being in force or in any instrument\n\nhaving effect by virtue of law other than this Act.\n\n26. Power to remove difficulties.—(1) If any difficulty arises in giving effect to the provisions of\n\nthis Act, the Central Government may, by order published in the Official Gazette, make such provisions\n\nnot inconsistent with the provisions of this Act as appear to it to be necessary or expedient for removing\n\nthe difficulty:\n\nProvided that no such order shall be made after the expiry of a period of two years from the date on\n\nwhich this Act receives the assent of the President.\n\n(2) Every order made under this section shall, as soon as may be after it is made, be laid before each\n\nHouse of Parliament.\n\n1[27. Power of Central Government to make rules.—(1) The Central Government in consultation\n\nwith the Chief Justice of India may, by notification, make rules to carry out the provisions of this Act.\n\n(2) In particular, and without prejudice to the generality of the foregoing power, such rules may\n\nprovide for all or any of the following matters, namely:—\n\n(a) the number, experience and qualifications of other members of the Central Authority under",
    "keywords": [],
    "document_type": "act",
    "jurisdiction": "India",
    "source": "THE LEGAL SERVICES AUTHORITIES ACT, 1987 .pdf",
    "importance": 5
  },
  {
    "id": "the-legal-services-authorities-act-1987-0027",
    "title": "THE LEGAL SERVICES AUTHORITIES ACT, 1987",
    "section": "",
    "category": "Legal",
    "text": "clause (c) of sub-section(2) of section3;\n\n(b) the experience and qualifications of the Member-Secretary of the Central Authority and his\n\npowers and functions under sub-section(3) of section3;\n\n(c) the terms of office and other conditions relating thereto, of members and Member-Secretary of\n\nthe Central Authority under sub-section(4) of section 3;\n\n(d) the number of officers and other employees of the Central Authority under sub-section(5) of\n\nsection3;\n\n(e) the conditions of service and the salary and allowances of officers and other employees of the\n\nCentral Authority under sub-section(6) of section3;\n\n(f) the number, experience and qualifications of members of the Supreme Court Legal Services\n\nCommittee under clause (b) of sub-section(2) of section 3A;\n\n(g) the experience and qualifications of Secretary of the Supreme Court Legal Services\n\nCommittee under sub-section(3) of section3A;\n\n1. Subs. by Act 59 of 1994, s. 18, for sections 27, 28 and 29 (w.e.f. 29-10-1994).\n\n(h) the number of officers and other employees of the Supreme Court Legal Services Committee\n\nunder sub-section(5) of section 3A and the conditions of service and the salary and allowances\n\npayable to them under sub-section(6) of that section;\n\n(i) the upper limit of annual income of a person entitling him to legal services under clause (h) of\n\nsection12, if the case is before the Supreme Court;\n\n(j) the manner in which the accounts of the Central Authority, the State Authority or the District\n\nAuthority shall be maintained under section18;\n\n(k) the experience and qualifications of other persons of the LokAdalatsorganised by the Supreme\n\nCourt Legal Services Committee specified in sub-section(3) of section19;\n\n(l) other matters under clause (e) of sub-section(1) of section22;\n\n1[(la) the other terms and conditions of appointment of the Chairman and other persons under\n\nsub-section (2) of section 22B;]\n\n(m) any other matter which is to be, or may be, prescribed.\n\n28. Power of State Government to make rules.—(1)The State Government in consultation with the",
    "keywords": [],
    "document_type": "act",
    "jurisdiction": "India",
    "source": "THE LEGAL SERVICES AUTHORITIES ACT, 1987 .pdf",
    "importance": 5
  },
  {
    "id": "the-legal-services-authorities-act-1987-0028",
    "title": "THE LEGAL SERVICES AUTHORITIES ACT, 1987",
    "section": "",
    "category": "Legal",
    "text": "Chief Justice of the High Court may, by notification, make rules to carry out the provisions of this Act.\n\n(2) In particular, and without prejudice to the generality of the foregoing power, such rules may\n\nprovide for all or any of the following matters, namely:—\n\n(a) the number, experience and qualifications of other members of the State Authority under\n\nclause (c) of sub-section(2) of section6;\n\n(b) the powers and functions of the Member-Secretary of the State Authority under sub-section(3)\n\nof section6;\n\n(c) the terms of office and other conditions relating thereto, of members and Member-Secretary of\n\nthe State Authority under sub-section(4) of section6;\n\n(d) the number of officers and other employees of the State Authority under sub-section(5) of\n\nsection6;\n\n(e) the conditions of service and the salary and allowances of officers and other employees of the\n\nState Authority under sub-section(6) of section6;\n\n(f) the experience and qualifications of Secretary of the High Court Legal Services Committee\n\nunder sub-section(3) of section 8A;\n\n(g) the number of officers and other employees of the High Court Legal Services Committee\n\nunder sub-section(5) of section 8A and the conditions of service and the salary and allowances\n\npayable to them under sub-section(6) of that section;\n\n(h) the number, experience and qualifications of members of the District Authority under clause\n\n(b) of sub-section(2) of section9;\n\n(i) the number of officers and other employees of the District Authority under sub-section(5) of\n\nsection9;\n\n(j) the conditions of service and the salary and allowances of the officers and other employees of\n\nthe District Authority under sub-section(6) of section9;\n\n(k) the number, experience and qualifications of members of the Taluk Legal Services Committee\n\nunder clause (b) of sub-section(2) of section 11A;\n\n(l) the number of officers and other employees of the Taluk Legal Services Committee under sub-\n\nsection(3) of section 11A;",
    "keywords": [],
    "document_type": "act",
    "jurisdiction": "India",
    "source": "THE LEGAL SERVICES AUTHORITIES ACT, 1987 .pdf",
    "importance": 5
  },
  {
    "id": "the-legal-services-authorities-act-1987-0029",
    "title": "THE LEGAL SERVICES AUTHORITIES ACT, 1987",
    "section": "",
    "category": "Legal",
    "text": "1. Ins. by Act 37 of 2002, s. 6 (w.e.f. 11-6-2002).\n\n(m) the conditions of service and the salary and allowances of officers and other employees of the\n\nTaluk Legal Services Committee under sub-section(4) of section 11A;\n\n(n) the upper limit of annual income of a person entitling him to legal services under clause (h)\n\nof section12, if the case is before a court, other than the Supreme Court;\n\n(o) the experience and qualifications of other persons of the LokAdalats other than referred to in\n\nsub-section(4) of section19;\n\n(p) any other matter which is to be, or may be, prescribed.\n\n29. Power of Central Authority to make regulations.—(1) The Central Authority may, by\n\nnotification, make regulations not inconsistent with the provisions of this Act and the rules made\n\nthereunder, to provide for all matters for which provisions is necessary or expedient for the purposes of\n\ngiving effect to the provisions of this Act.\n\n(2) In particular, and without prejudice to the generality of the foregoing power, such regulations may\n\nprovide for all or any of the following matters, namely:—\n\n(a) the powers and functions of the Supreme Court Legal Services Committee under sub-\n\nsection(1) of section3A;\n\n(b) the terms of office and other conditions relating thereto, of the members and Secretary of the\n\nSupreme Court Legal Services Committee under sub-section(4) of section3A.\n\n29A. Power of State Authority to make regulations.—(1) The State Authority may, by\n\nnotification, make regulations not inconsistent with the provisions of this Act and the rules made\n\nthereunder, to provide for all matters for which provision in necessary or expedient for the purposes of\n\ngiving effect to the provisions of this Act.\n\n(2) In particular, and without prejudice to the generality of the foregoing power, such regulations may\n\nprovide for all or any of the following matters, namely:—",
    "keywords": [],
    "document_type": "act",
    "jurisdiction": "India",
    "source": "THE LEGAL SERVICES AUTHORITIES ACT, 1987 .pdf",
    "importance": 5
  },
  {
    "id": "the-legal-services-authorities-act-1987-0030",
    "title": "THE LEGAL SERVICES AUTHORITIES ACT, 1987",
    "section": "",
    "category": "Legal",
    "text": "(a) the other functions to be performed by the State Authority under clause (d) of sub-section(2)\n\nof section7;\n\n(b) the powers and functions of the High Court Legal Services Committee under sub-section(1) of\n\nsection8A;\n\n(c) the number, experience and qualifications of members of the High Court Legal Services\n\nCommittee under clause (b) of sub-section(2) of section8A;\n\n(d) the terms of office and other conditions relating thereto, of the members and Secretary of the\n\nHigh Court Legal Services Committee under sub-section(4) of section8A;\n\n(e) the term of office and other conditions relating thereto, of the members and Secretary of the\n\nDistrict Authority under sub-section(4) of section9;\n\n(f) the number, experience and qualifications of members of the High Court Legal Services\n\nCommittee under clause (b) of sub-section(2) of section 8A;\n\n(g) other functions to be performed by the District Authority under clause (c) of sub-section(2) of\n\nsection10;\n\n(h) the term of office and other conditions relating thereto, of members and Secretary of the Taluk\n\nLegal Services Committee under sub-section(3) of section 11A.]\n\n30. Laying of rules and regulations.—(1) Every rule made under this Act by the Central\n\nGovernment and every regulation made by the Central Authority thereunder shall be laid, as soon as may\n\nbe after it is made, before each House of Parliament, while it is in session, for a total period of thirty days\n\nwhich may be comprised in one session, or in two or more successive sessions, and if, before the expiry\n\nof the session immediately following the session or the successive sessions aforesaid, both Houses agree\n\nin making any modification in the rule or regulation, or both Houses agree that the rule or regulation\n\nshould not be made, the rule or regulation shall thereafter have effect only in such modified form or be of\n\nno effect, as the case may be; so, however, that any such modification or annulment shall be without",
    "keywords": [],
    "document_type": "act",
    "jurisdiction": "India",
    "source": "THE LEGAL SERVICES AUTHORITIES ACT, 1987 .pdf",
    "importance": 5
  },
  {
    "id": "the-legal-services-authorities-act-1987-0031",
    "title": "THE LEGAL SERVICES AUTHORITIES ACT, 1987",
    "section": "",
    "category": "Legal",
    "text": "prejudice to the validity of anything previously done under that rule or regulation.\n\n(2) Every rule made under this Act by a State Government and every regulation made by a State\n\nAuthority thereunder shall be laid, as soon as may be after it is made, before the State Legislature.",
    "keywords": [],
    "document_type": "act",
    "jurisdiction": "India",
    "source": "THE LEGAL SERVICES AUTHORITIES ACT, 1987 .pdf",
    "importance": 5
  }
]